playbook_runner/__init__.py
playbook_runner/parent_play.tmplt
playbook_runner/playbook_runner.py
playbook_runner/version.py
playbook_runner-0.2.18.dist-info/LICENSE
playbook_runner-0.2.18.dist-info/METADATA
playbook_runner-0.2.18.dist-info/WHEEL
playbook_runner-0.2.18.dist-info/top_level.txt
playbook_runner-0.2.18.dist-info/RECORD
