Metadata-Version: 2.1
Name: playbook-runner
Version: 0.2.18
Summary: A module that is capable of running ansible playbooks
Home-page: https://github.com/final-israel/playbook_runner
Author: Pavel Rogovoy
Author-email: pavelr@final.israel
License: UNKNOWN
Platform: UNKNOWN
